.DS_Store
sortasurvey/__init__.py
sortasurvey/cli.py
sortasurvey/notebook.py
sortasurvey/observing.py
sortasurvey/pipeline.py
sortasurvey/sample.py
sortasurvey/survey.py
sortasurvey/utils.py
sortasurvey-1.1.0.dist-info/LICENSE
sortasurvey-1.1.0.dist-info/METADATA
sortasurvey-1.1.0.dist-info/WHEEL
sortasurvey-1.1.0.dist-info/entry_points.txt
sortasurvey-1.1.0.dist-info/top_level.txt
sortasurvey-1.1.0.dist-info/RECORD
