Metadata-Version: 2.1
Name: sortasurvey
Version: 1.1.0
Summary: Automated and reproducible target selection for large collaborations
Home-page: https://github.com/ashleychontos/sort-a-survey
Author: Ashley Chontos
Author-email: achontos@hawaii.edu
License: MIT
Project-URL: Documentation, https://sortasurvey.readthedocs.io
Project-URL: Source, https://github.com/ashleychontos/sort-a-survey
Project-URL: Bug Tracker, https://github.com/ashleychontos/sort-a-survey/issues
Platform: UNKNOWN
Classifier: Programming Language :: Python :: 3
Classifier: License :: OSI Approved :: MIT License
Classifier: Operating System :: OS Independent
Requires-Python: >=3.6
License-File: LICENSE
Requires-Dist: numpy (>=1.16)
Requires-Dist: pandas (>=1.0.5)
Requires-Dist: scipy
Requires-Dist: tqdm
